NDL_codes/__init__.py
NDL_codes/lab_10.py
NDL_codes/lab_11.py
NDL_codes/lab_12a.py
NDL_codes/lab_12b.py
NDL_codes/lab_12c.py
NDL_codes/lab_1b.py
NDL_codes/lab_1b_part2.py
NDL_codes/lab_2.py
NDL_codes/lab_3a.py
NDL_codes/lab_3a_part2.py
NDL_codes/lab_3b.py
NDL_codes/lab_4.py
NDL_codes/lab_5.py
NDL_codes/lab_6a.py
NDL_codes/lab_6b.py
NDL_codes/lab_7a.py
NDL_codes/lab_7b.py
NDL_codes/lab_8.py
NDL_codes/lab_9.py
ndl_lab-0.1.2.dist-info/licenses/LICENSE.txt
ndl_lab-0.1.2.dist-info/METADATA
ndl_lab-0.1.2.dist-info/WHEEL
ndl_lab-0.1.2.dist-info/top_level.txt
ndl_lab-0.1.2.dist-info/RECORD
